<?xml version="1.0" encoding="UTF-8"?>
<!-- Product Version: Vivado v2016.2 (64-bit)                     -->
<!--                                                              -->
<!-- Copyright 1986-2016 Xilinx, Inc. All Rights Reserved.        -->

<hwsession version="1" minor="1">
  <device name="xc7a35t_0" gui_info="dashboard1=hw_ila_1[xc7a35t_0/hw_ila_1/Settings=ILA_SETTINGS_1;xc7a35t_0/hw_ila_1/Status=ILA_STATUS_1;xc7a35t_0/hw_ila_1/Trigger Setup=ILA_TRIGGER_1;xc7a35t_0/hw_ila_1/Waveform=ILA_WAVE_1;xc7a35t_0/hw_ila_1/Capture Setup=ILA_CAPTURE_1;]"/>
  <ObjectList object_type="hw_device" gui_info="">
    <Object name="xc7a35t_0" gui_info="">
      <Properties Property="PROBES.FILE" value="$_project_name_.runs/impl_1/debug_nets.ltx"/>
      <Properties Property="PROGRAM.HW_BITSTREAM" value="$_project_name_.runs/impl_1/$_project_name_.bit"/>
    </Object>
  </ObjectList>
  <ObjectList object_type="hw_ila" gui_info="">
    <Object name="hw_ila_1" gui_info="">
      <Properties Property="CONTROL.TRIGGER_CONDITION" value="AND"/>
      <Properties Property="CORE_REFRESH_RATE_MS" value="500"/>
    </Object>
    <Object name="u3_usb_controller/uut_ila" gui_info="">
      <Properties Property="CONTROL.TRIGGER_CONDITION" value="AND"/>
      <Properties Property="CONTROL.TRIGGER_POSITION" value="128"/>
      <Properties Property="CORE_REFRESH_RATE_MS" value="500"/>
    </Object>
  </ObjectList>
  <ObjectList object_type="hw_probe" gui_info="">
    <Object name="u3_usb_controller/fx3_slcs_n" gui_info="Trigger Setup=0"/>
  </ObjectList>
  <probeset name="hw project" active="false">
    <probe type="ila" busType="bus" source="netlist" spec="ILA_V2_RT">
      <probeOptions Id="DebugProbeParams">
        <Option Id="CAPTURE_COMPARE_VALUE" value="eq2&apos;hX"/>
        <Option Id="COMPARE_VALUE.0" value="eq2&apos;hX"/>
        <Option Id="DISPLAY_HINT" value=""/>
        <Option Id="DISPLAY_VISIBILITY" value=""/>
        <Option Id="HW_ILA" value="hw_ila_1"/>
        <Option Id="MAP" value="probe1[1:0]"/>
        <Option Id="NAME.CUSTOM" value=""/>
        <Option Id="NAME.SELECT" value="Long"/>
        <Option Id="SOURCE" value="netlist"/>
        <Option Id="TRIGGER_COMPARE_VALUE" value="eq2&apos;hX"/>
      </probeOptions>
      <nets>
        <net name="u3_usb_controller/fx3_a[1]"/>
        <net name="u3_usb_controller/fx3_a[0]"/>
      </nets>
    </probe>
    <probe type="ila" busType="bus" source="netlist" spec="ILA_V2_RT">
      <probeOptions Id="DebugProbeParams">
        <Option Id="CAPTURE_COMPARE_VALUE" value="eq32&apos;hXXXX_XXXX"/>
        <Option Id="COMPARE_VALUE.0" value="eq32&apos;hXXXX_XXXX"/>
        <Option Id="DISPLAY_HINT" value=""/>
        <Option Id="DISPLAY_VISIBILITY" value=""/>
        <Option Id="HW_ILA" value="hw_ila_1"/>
        <Option Id="MAP" value="probe2[31:0]"/>
        <Option Id="NAME.CUSTOM" value=""/>
        <Option Id="NAME.SELECT" value="Long"/>
        <Option Id="SOURCE" value="netlist"/>
        <Option Id="TRIGGER_COMPARE_VALUE" value="eq32&apos;hXXXX_XXXX"/>
      </probeOptions>
      <nets>
        <net name="u3_usb_controller/fx3_db[31]"/>
        <net name="u3_usb_controller/fx3_db[30]"/>
        <net name="u3_usb_controller/fx3_db[29]"/>
        <net name="u3_usb_controller/fx3_db[28]"/>
        <net name="u3_usb_controller/fx3_db[27]"/>
        <net name="u3_usb_controller/fx3_db[26]"/>
        <net name="u3_usb_controller/fx3_db[25]"/>
        <net name="u3_usb_controller/fx3_db[24]"/>
        <net name="u3_usb_controller/fx3_db[23]"/>
        <net name="u3_usb_controller/fx3_db[22]"/>
        <net name="u3_usb_controller/fx3_db[21]"/>
        <net name="u3_usb_controller/fx3_db[20]"/>
        <net name="u3_usb_controller/fx3_db[19]"/>
        <net name="u3_usb_controller/fx3_db[18]"/>
        <net name="u3_usb_controller/fx3_db[17]"/>
        <net name="u3_usb_controller/fx3_db[16]"/>
        <net name="u3_usb_controller/fx3_db[15]"/>
        <net name="u3_usb_controller/fx3_db[14]"/>
        <net name="u3_usb_controller/fx3_db[13]"/>
        <net name="u3_usb_controller/fx3_db[12]"/>
        <net name="u3_usb_controller/fx3_db[11]"/>
        <net name="u3_usb_controller/fx3_db[10]"/>
        <net name="u3_usb_controller/fx3_db[9]"/>
        <net name="u3_usb_controller/fx3_db[8]"/>
        <net name="u3_usb_controller/fx3_db[7]"/>
        <net name="u3_usb_controller/fx3_db[6]"/>
        <net name="u3_usb_controller/fx3_db[5]"/>
        <net name="u3_usb_controller/fx3_db[4]"/>
        <net name="u3_usb_controller/fx3_db[3]"/>
        <net name="u3_usb_controller/fx3_db[2]"/>
        <net name="u3_usb_controller/fx3_db[1]"/>
        <net name="u3_usb_controller/fx3_db[0]"/>
      </nets>
    </probe>
    <probe type="ila" busType="net" source="netlist" spec="ILA_V2_RT">
      <probeOptions Id="DebugProbeParams">
        <Option Id="CAPTURE_COMPARE_VALUE" value="eq1&apos;bX"/>
        <Option Id="COMPARE_VALUE.0" value="eq1&apos;bX"/>
        <Option Id="DISPLAY_HINT" value=""/>
        <Option Id="DISPLAY_VISIBILITY" value=""/>
        <Option Id="HW_ILA" value="hw_ila_1"/>
        <Option Id="MAP" value="probe0[6]"/>
        <Option Id="NAME.CUSTOM" value=""/>
        <Option Id="NAME.SELECT" value="Long"/>
        <Option Id="SOURCE" value="netlist"/>
        <Option Id="TRIGGER_COMPARE_VALUE" value="eq1&apos;bX"/>
      </probeOptions>
      <nets>
        <net name="u3_usb_controller/fx3_flaga"/>
      </nets>
    </probe>
    <probe type="ila" busType="net" source="netlist" spec="ILA_V2_RT">
      <probeOptions Id="DebugProbeParams">
        <Option Id="CAPTURE_COMPARE_VALUE" value="eq1&apos;bX"/>
        <Option Id="COMPARE_VALUE.0" value="eq1&apos;bX"/>
        <Option Id="DISPLAY_HINT" value=""/>
        <Option Id="DISPLAY_VISIBILITY" value=""/>
        <Option Id="HW_ILA" value="hw_ila_1"/>
        <Option Id="MAP" value="probe0[5]"/>
        <Option Id="NAME.CUSTOM" value=""/>
        <Option Id="NAME.SELECT" value="Long"/>
        <Option Id="SOURCE" value="netlist"/>
        <Option Id="TRIGGER_COMPARE_VALUE" value="eq1&apos;bX"/>
      </probeOptions>
      <nets>
        <net name="u3_usb_controller/fx3_flagb"/>
      </nets>
    </probe>
    <probe type="ila" busType="net" source="netlist" spec="ILA_V2_RT">
      <probeOptions Id="DebugProbeParams">
        <Option Id="CAPTURE_COMPARE_VALUE" value="eq1&apos;bX"/>
        <Option Id="COMPARE_VALUE.0" value="eq1&apos;bX"/>
        <Option Id="DISPLAY_HINT" value=""/>
        <Option Id="DISPLAY_VISIBILITY" value=""/>
        <Option Id="HW_ILA" value="hw_ila_1"/>
        <Option Id="MAP" value="probe0[0]"/>
        <Option Id="NAME.CUSTOM" value=""/>
        <Option Id="NAME.SELECT" value="Long"/>
        <Option Id="SOURCE" value="netlist"/>
        <Option Id="TRIGGER_COMPARE_VALUE" value="eq1&apos;bX"/>
      </probeOptions>
      <nets>
        <net name="u3_usb_controller/fx3_pktend_n"/>
      </nets>
    </probe>
    <probe type="ila" busType="bus" source="netlist" spec="ILA_V2_RT">
      <probeOptions Id="DebugProbeParams">
        <Option Id="CAPTURE_COMPARE_VALUE" value="eq32&apos;hXXXX_XXXX"/>
        <Option Id="COMPARE_VALUE.0" value="eq32&apos;hXXXX_XXXX"/>
        <Option Id="DISPLAY_HINT" value=""/>
        <Option Id="DISPLAY_VISIBILITY" value=""/>
        <Option Id="HW_ILA" value="hw_ila_1"/>
        <Option Id="MAP" value="probe5[31:0]"/>
        <Option Id="NAME.CUSTOM" value=""/>
        <Option Id="NAME.SELECT" value="Long"/>
        <Option Id="SOURCE" value="netlist"/>
        <Option Id="TRIGGER_COMPARE_VALUE" value="eq32&apos;hXXXX_XXXX"/>
      </probeOptions>
      <nets>
        <net name="u3_usb_controller/fx3_rdb[31]"/>
        <net name="u3_usb_controller/fx3_rdb[30]"/>
        <net name="u3_usb_controller/fx3_rdb[29]"/>
        <net name="u3_usb_controller/fx3_rdb[28]"/>
        <net name="u3_usb_controller/fx3_rdb[27]"/>
        <net name="u3_usb_controller/fx3_rdb[26]"/>
        <net name="u3_usb_controller/fx3_rdb[25]"/>
        <net name="u3_usb_controller/fx3_rdb[24]"/>
        <net name="u3_usb_controller/fx3_rdb[23]"/>
        <net name="u3_usb_controller/fx3_rdb[22]"/>
        <net name="u3_usb_controller/fx3_rdb[21]"/>
        <net name="u3_usb_controller/fx3_rdb[20]"/>
        <net name="u3_usb_controller/fx3_rdb[19]"/>
        <net name="u3_usb_controller/fx3_rdb[18]"/>
        <net name="u3_usb_controller/fx3_rdb[17]"/>
        <net name="u3_usb_controller/fx3_rdb[16]"/>
        <net name="u3_usb_controller/fx3_rdb[15]"/>
        <net name="u3_usb_controller/fx3_rdb[14]"/>
        <net name="u3_usb_controller/fx3_rdb[13]"/>
        <net name="u3_usb_controller/fx3_rdb[12]"/>
        <net name="u3_usb_controller/fx3_rdb[11]"/>
        <net name="u3_usb_controller/fx3_rdb[10]"/>
        <net name="u3_usb_controller/fx3_rdb[9]"/>
        <net name="u3_usb_controller/fx3_rdb[8]"/>
        <net name="u3_usb_controller/fx3_rdb[7]"/>
        <net name="u3_usb_controller/fx3_rdb[6]"/>
        <net name="u3_usb_controller/fx3_rdb[5]"/>
        <net name="u3_usb_controller/fx3_rdb[4]"/>
        <net name="u3_usb_controller/fx3_rdb[3]"/>
        <net name="u3_usb_controller/fx3_rdb[2]"/>
        <net name="u3_usb_controller/fx3_rdb[1]"/>
        <net name="u3_usb_controller/fx3_rdb[0]"/>
      </nets>
    </probe>
    <probe type="ila" busType="net" source="netlist" spec="ILA_V2_RT">
      <probeOptions Id="DebugProbeParams">
        <Option Id="CAPTURE_COMPARE_VALUE" value="eq1&apos;bX"/>
        <Option Id="COMPARE_VALUE.0" value="eq1&apos;bX"/>
        <Option Id="DISPLAY_HINT" value=""/>
        <Option Id="DISPLAY_VISIBILITY" value=""/>
        <Option Id="HW_ILA" value="hw_ila_1"/>
        <Option Id="MAP" value="probe3[0]"/>
        <Option Id="NAME.CUSTOM" value=""/>
        <Option Id="NAME.SELECT" value="Long"/>
        <Option Id="SOURCE" value="netlist"/>
        <Option Id="TRIGGER_COMPARE_VALUE" value="eq1&apos;bX"/>
      </probeOptions>
      <nets>
        <net name="u3_usb_controller/fx3_rdb_en"/>
      </nets>
    </probe>
    <probe type="ila" busType="net" source="netlist" spec="ILA_V2_RT">
      <probeOptions Id="DebugProbeParams">
        <Option Id="CAPTURE_COMPARE_VALUE" value="eq1&apos;bX"/>
        <Option Id="COMPARE_VALUE.0" value="eq1&apos;bF"/>
        <Option Id="DISPLAY_HINT" value=""/>
        <Option Id="DISPLAY_VISIBILITY" value=""/>
        <Option Id="HW_ILA" value="hw_ila_1"/>
        <Option Id="MAP" value="probe0[4]"/>
        <Option Id="NAME.CUSTOM" value=""/>
        <Option Id="NAME.SELECT" value="Long"/>
        <Option Id="SOURCE" value="netlist"/>
        <Option Id="TRIGGER_COMPARE_VALUE" value="eq1&apos;bF"/>
      </probeOptions>
      <nets>
        <net name="u3_usb_controller/fx3_slcs_n"/>
      </nets>
    </probe>
    <probe type="ila" busType="net" source="netlist" spec="ILA_V2_RT">
      <probeOptions Id="DebugProbeParams">
        <Option Id="CAPTURE_COMPARE_VALUE" value="eq1&apos;bX"/>
        <Option Id="COMPARE_VALUE.0" value="eq1&apos;bX"/>
        <Option Id="DISPLAY_HINT" value=""/>
        <Option Id="DISPLAY_VISIBILITY" value=""/>
        <Option Id="HW_ILA" value="hw_ila_1"/>
        <Option Id="MAP" value="probe0[1]"/>
        <Option Id="NAME.CUSTOM" value=""/>
        <Option Id="NAME.SELECT" value="Long"/>
        <Option Id="SOURCE" value="netlist"/>
        <Option Id="TRIGGER_COMPARE_VALUE" value="eq1&apos;bX"/>
      </probeOptions>
      <nets>
        <net name="u3_usb_controller/fx3_sloe_n"/>
      </nets>
    </probe>
    <probe type="ila" busType="net" source="netlist" spec="ILA_V2_RT">
      <probeOptions Id="DebugProbeParams">
        <Option Id="CAPTURE_COMPARE_VALUE" value="eq1&apos;bX"/>
        <Option Id="COMPARE_VALUE.0" value="eq1&apos;bX"/>
        <Option Id="DISPLAY_HINT" value=""/>
        <Option Id="DISPLAY_VISIBILITY" value=""/>
        <Option Id="HW_ILA" value="hw_ila_1"/>
        <Option Id="MAP" value="probe0[2]"/>
        <Option Id="NAME.CUSTOM" value=""/>
        <Option Id="NAME.SELECT" value="Long"/>
        <Option Id="SOURCE" value="netlist"/>
        <Option Id="TRIGGER_COMPARE_VALUE" value="eq1&apos;bX"/>
      </probeOptions>
      <nets>
        <net name="u3_usb_controller/fx3_slrd_n"/>
      </nets>
    </probe>
    <probe type="ila" busType="net" source="netlist" spec="ILA_V2_RT">
      <probeOptions Id="DebugProbeParams">
        <Option Id="CAPTURE_COMPARE_VALUE" value="eq1&apos;bX"/>
        <Option Id="COMPARE_VALUE.0" value="eq1&apos;bX"/>
        <Option Id="DISPLAY_HINT" value=""/>
        <Option Id="DISPLAY_VISIBILITY" value=""/>
        <Option Id="HW_ILA" value="hw_ila_1"/>
        <Option Id="MAP" value="probe0[3]"/>
        <Option Id="NAME.CUSTOM" value=""/>
        <Option Id="NAME.SELECT" value="Long"/>
        <Option Id="SOURCE" value="netlist"/>
        <Option Id="TRIGGER_COMPARE_VALUE" value="eq1&apos;bX"/>
      </probeOptions>
      <nets>
        <net name="u3_usb_controller/fx3_slwr_n"/>
      </nets>
    </probe>
    <probe type="ila" busType="bus" source="netlist" spec="ILA_V2_RT">
      <probeOptions Id="DebugProbeParams">
        <Option Id="CAPTURE_COMPARE_VALUE" value="eq8&apos;hXX"/>
        <Option Id="COMPARE_VALUE.0" value="eq8&apos;hXX"/>
        <Option Id="DISPLAY_HINT" value=""/>
        <Option Id="DISPLAY_VISIBILITY" value=""/>
        <Option Id="HW_ILA" value="hw_ila_1"/>
        <Option Id="MAP" value="probe4[7:0]"/>
        <Option Id="NAME.CUSTOM" value=""/>
        <Option Id="NAME.SELECT" value="Long"/>
        <Option Id="SOURCE" value="netlist"/>
        <Option Id="TRIGGER_COMPARE_VALUE" value="eq8&apos;hXX"/>
      </probeOptions>
      <nets>
        <net name="u3_usb_controller/ram_addr[7]"/>
        <net name="u3_usb_controller/ram_addr[6]"/>
        <net name="u3_usb_controller/ram_addr[5]"/>
        <net name="u3_usb_controller/ram_addr[4]"/>
        <net name="u3_usb_controller/ram_addr[3]"/>
        <net name="u3_usb_controller/ram_addr[2]"/>
        <net name="u3_usb_controller/ram_addr[1]"/>
        <net name="u3_usb_controller/ram_addr[0]"/>
      </nets>
    </probe>
  </probeset>
</hwsession>
